README.md
setup.py
wingman.log
icons/general/wingman.png
packaging/linux/eu.biqqles.wingman.desktop
src/wingman/__init__.py
src/wingman/main.py
src/wingman/namespaces.py
src/wingman/resources.py
src/wingman.egg-info/PKG-INFO
src/wingman.egg-info/SOURCES.txt
src/wingman.egg-info/dependency_links.txt
src/wingman.egg-info/entry_points.txt
src/wingman.egg-info/requires.txt
src/wingman.egg-info/top_level.txt
src/wingman/models/filters.py
src/wingman/models/items.py
src/wingman/models/selectors.py
src/wingman/models/special/accounts.py
src/wingman/widgets/buttons.py
src/wingman/widgets/infocardview.py
src/wingman/widgets/pathedit.py
src/wingman/widgets/scrollablelist.py
src/wingman/widgets/simpletable.py
src/wingman/widgets/simpletree.py
src/wingman/widgets/mapview/__init__.py
src/wingman/widgets/mapview/mapview.py
src/wingman/windows/boxes/about.py
src/wingman/windows/boxes/configuration.py
src/wingman/windows/boxes/error.py
src/wingman/windows/boxes/expandedmap.py
src/wingman/windows/database/layout.py
src/wingman/windows/database/pages.py
src/wingman/windows/main/banner.py
src/wingman/windows/main/layout.py
src/wingman/windows/main/loading.py
src/wingman/windows/main/menus.py
src/wingman/windows/main/merchant/__init__.py
src/wingman/windows/main/merchant/layout.py
src/wingman/windows/main/merchant/merchant.py
src/wingman/windows/main/navmap/__init__.py
src/wingman/windows/main/navmap/layout.py
src/wingman/windows/main/navmap/navmap.py
src/wingman/windows/main/roster/__init__.py
src/wingman/windows/main/roster/layout.py
src/wingman/windows/main/roster/roster.py