Metadata-Version: 2.1
Name: wingman
Version: 5.1
Summary: A companion for Discovery Freelancer
Home-page: https://discoverygc.com/forums/showthread.php?tid=150721
Author: biqqles
Author-email: biqqles@protonmail.com
License: UNKNOWN
Platform: UNKNOWN
Classifier: Programming Language :: Python :: 3
Classifier: License :: OSI Approved :: GNU General Public License v3 (GPLv3)
Classifier: Development Status :: 4 - Beta
Classifier: Operating System :: POSIX :: Linux
Classifier: Operating System :: Microsoft :: Windows
Classifier: Topic :: Games/Entertainment
Classifier: Intended Audience :: End Users/Desktop
Classifier: Environment :: X11 Applications :: Qt
Requires-Python: >=3.7
